sdssviz_ca25/__init__.py
sdssviz_ca25/animation.py
sdssviz_ca25/example_case.py
sdssviz_ca25/interactive_plot.py
sdssviz_ca25/package_skeleton.py
sdssviz_ca25/testing.py
sdssviz_ca25/unit_tests.py
sdssviz_ca25/old_code/get_sdss_data.py
sdssviz_ca25/old_code/package.py
sdssviz_ca25/old_code/plot_spectra_fits.py
sdssviz_ca25-1.0.0.dist-info/licenses/LICENSE
sdssviz_ca25-1.0.0.dist-info/METADATA
sdssviz_ca25-1.0.0.dist-info/WHEEL
sdssviz_ca25-1.0.0.dist-info/top_level.txt
sdssviz_ca25-1.0.0.dist-info/RECORD
