Metadata-Version: 2.4
Name: sdssviz_ca25
Version: 1.0.0
License-File: LICENSE
Requires-Dist: numpy
Requires-Dist: matplotlib
Requires-Dist: astroquery
Requires-Dist: mplcursors
Dynamic: license-file
